jadio_bugchecker/__init__.py
jadio_bugchecker/cli/__init__.py
jadio_bugchecker/cli/clicommands.json
jadio_bugchecker-0.0.1.dist-info/METADATA
jadio_bugchecker-0.0.1.dist-info/WHEEL
jadio_bugchecker-0.0.1.dist-info/entry_points.txt
jadio_bugchecker-0.0.1.dist-info/licenses/LICENSE
jadio_bugchecker-0.0.1.dist-info/RECORD
